<?xml version="1.0" encoding="UTF-8" ?>
<!DOCTYPE struts PUBLIC "-//Apache Software Foundation//DTD Struts Configuration 2.0//EN" "http://struts.apache.org/dtds/struts-2.0.dtd">
    
<struts>
	<package name="struts_twoTeam_package" namespace="/" extends="struts-default, tiles-default">
		
		<action name="insertMembers" class="members.MembersAction" method="home">
			<result name="success" type="tiles">MembersForm</result>
		</action>
		
		
		<action name="successMembers" class="members.MembersAction" method="Insert">
			<result name="success" type="tiles">insertMembers</result>
		</action>
		
		

	</package>
</struts>